edhsmm/__init__.py
edhsmm/_hsmm_core.cp310-win_amd64.pyd
edhsmm/hsmm_base.py
edhsmm/hsmm_multinom.py
edhsmm/hsmm_utils.py
edhsmm-0.2.2.dist-info/LICENSE.txt
edhsmm-0.2.2.dist-info/METADATA
edhsmm-0.2.2.dist-info/WHEEL
edhsmm-0.2.2.dist-info/top_level.txt
edhsmm-0.2.2.dist-info/RECORD
