Metadata-Version: 2.1
Name: edhsmm
Version: 0.2.2
Summary: An(other) implementation of Explicit Duration Hidden Semi-Markov Models in Python 3
Home-page: https://github.com/poypoyan/edhsmm
Author: poypoyan
Author-email: srazin123@gmail.com
License: MIT
Classifier: Development Status :: 3 - Alpha
Classifier: License :: OSI Approved
Classifier: Intended Audience :: Developers
Classifier: Intended Audience :: Science/Research
Classifier: Topic :: Software Development
Classifier: Topic :: Scientific/Engineering
Classifier: Programming Language :: Cython
Classifier: Programming Language :: Python :: 3
Requires-Python: >=3.5
License-File: LICENSE.txt
Requires-Dist: numpy (>=1.17)
Requires-Dist: scikit-learn (>=0.16)
Requires-Dist: scipy (>=0.19)
